{"dependencies":[{"name":"C:\\Users\\Ahmed\\Desktop\\Natours\\package.json","includedInParent":true,"mtime":1685934625119},{"name":"C:\\Users\\Ahmed\\Desktop\\Natours\\node_modules\\pako\\package.json","includedInParent":true,"mtime":1684371851851}],"generated":{"js":"'use strict';\r\n\r\n// Note: we can't get significant speed boost here.\r\n// So write code to minimize size - no pregenerated tables\r\n// and array tools dependencies.\r\n\r\n// (C) 1995-2013 Jean-loup Gailly and Mark Adler\r\n// (C) 2014-2017 Vitaly Puzrin and Andrey Tupitsin\r\n//\r\n// This software is provided 'as-is', without any express or implied\r\n// warranty. In no event will the authors be held liable for any damages\r\n// arising from the use of this software.\r\n//\r\n// Permission is granted to anyone to use this software for any purpose,\r\n// including commercial applications, and to alter it and redistribute it\r\n// freely, subject to the following restrictions:\r\n//\r\n// 1. The origin of this software must not be misrepresented; you must not\r\n//   claim that you wrote the original software. If you use this software\r\n//   in a product, an acknowledgment in the product documentation would be\r\n//   appreciated but is not required.\r\n// 2. Altered source versions must be plainly marked as such, and must not be\r\n//   misrepresented as being the original software.\r\n// 3. This notice may not be removed or altered from any source distribution.\r\n\r\n// Use ordinary array, since untyped makes no boost here\r\nfunction makeTable() {\r\n  var c, table = [];\r\n\r\n  for (var n = 0; n < 256; n++) {\r\n    c = n;\r\n    for (var k = 0; k < 8; k++) {\r\n      c = ((c & 1) ? (0xEDB88320 ^ (c >>> 1)) : (c >>> 1));\r\n    }\r\n    table[n] = c;\r\n  }\r\n\r\n  return table;\r\n}\r\n\r\n// Create table on load. Just 255 signed longs. Not a problem.\r\nvar crcTable = makeTable();\r\n\r\n\r\nfunction crc32(crc, buf, len, pos) {\r\n  var t = crcTable,\r\n      end = pos + len;\r\n\r\n  crc ^= -1;\r\n\r\n  for (var i = pos; i < end; i++) {\r\n    crc = (crc >>> 8) ^ t[(crc ^ buf[i]) & 0xFF];\r\n  }\r\n\r\n  return (crc ^ (-1)); // >>> 0;\r\n}\r\n\r\n\r\nmodule.exports = crc32;\r\n","map":{"mappings":[{"source":"..\\..\\node_modules\\pako\\lib\\zlib\\crc32.js","original":{"line":1,"column":0},"generated":{"line":1,"column":0}},{"source":"..\\..\\node_modules\\pako\\lib\\zlib\\crc32.js","original":{"line":2,"column":0},"generated":{"line":2,"column":0}},{"source":"..\\..\\node_modules\\pako\\lib\\zlib\\crc32.js","original":{"line":3,"column":0},"generated":{"line":3,"column":0}},{"source":"..\\..\\node_modules\\pako\\lib\\zlib\\crc32.js","original":{"line":4,"column":0},"generated":{"line":4,"column":0}},{"source":"..\\..\\node_modules\\pako\\lib\\zlib\\crc32.js","original":{"line":5,"column":0},"generated":{"line":5,"column":0}},{"source":"..\\..\\node_modules\\pako\\lib\\zlib\\crc32.js","original":{"line":6,"column":0},"generated":{"line":6,"column":0}},{"source":"..\\..\\node_modules\\pako\\lib\\zlib\\crc32.js","original":{"line":7,"column":0},"generated":{"line":7,"column":0}},{"source":"..\\..\\node_modules\\pako\\lib\\zlib\\crc32.js","original":{"line":8,"column":0},"generated":{"line":8,"column":0}},{"source":"..\\..\\node_modules\\pako\\lib\\zlib\\crc32.js","original":{"line":9,"column":0},"generated":{"line":9,"column":0}},{"source":"..\\..\\node_modules\\pako\\lib\\zlib\\crc32.js","original":{"line":10,"column":0},"generated":{"line":10,"column":0}},{"source":"..\\..\\node_modules\\pako\\lib\\zlib\\crc32.js","original":{"line":11,"column":0},"generated":{"line":11,"column":0}},{"source":"..\\..\\node_modules\\pako\\lib\\zlib\\crc32.js","original":{"line":12,"column":0},"generated":{"line":12,"column":0}},{"source":"..\\..\\node_modules\\pako\\lib\\zlib\\crc32.js","original":{"line":13,"column":0},"generated":{"line":13,"column":0}},{"source":"..\\..\\node_modules\\pako\\lib\\zlib\\crc32.js","original":{"line":14,"column":0},"generated":{"line":14,"column":0}},{"source":"..\\..\\node_modules\\pako\\lib\\zlib\\crc32.js","original":{"line":15,"column":0},"generated":{"line":15,"column":0}},{"source":"..\\..\\node_modules\\pako\\lib\\zlib\\crc32.js","original":{"line":16,"column":0},"generated":{"line":16,"column":0}},{"source":"..\\..\\node_modules\\pako\\lib\\zlib\\crc32.js","original":{"line":17,"column":0},"generated":{"line":17,"column":0}},{"source":"..\\..\\node_modules\\pako\\lib\\zlib\\crc32.js","original":{"line":18,"column":0},"generated":{"line":18,"column":0}},{"source":"..\\..\\node_modules\\pako\\lib\\zlib\\crc32.js","original":{"line":19,"column":0},"generated":{"line":19,"column":0}},{"source":"..\\..\\node_modules\\pako\\lib\\zlib\\crc32.js","original":{"line":20,"column":0},"generated":{"line":20,"column":0}},{"source":"..\\..\\node_modules\\pako\\lib\\zlib\\crc32.js","original":{"line":21,"column":0},"generated":{"line":21,"column":0}},{"source":"..\\..\\node_modules\\pako\\lib\\zlib\\crc32.js","original":{"line":22,"column":0},"generated":{"line":22,"column":0}},{"source":"..\\..\\node_modules\\pako\\lib\\zlib\\crc32.js","original":{"line":23,"column":0},"generated":{"line":23,"column":0}},{"source":"..\\..\\node_modules\\pako\\lib\\zlib\\crc32.js","original":{"line":24,"column":0},"generated":{"line":24,"column":0}},{"source":"..\\..\\node_modules\\pako\\lib\\zlib\\crc32.js","original":{"line":25,"column":0},"generated":{"line":25,"column":0}},{"source":"..\\..\\node_modules\\pako\\lib\\zlib\\crc32.js","original":{"line":26,"column":0},"generated":{"line":26,"column":0}},{"source":"..\\..\\node_modules\\pako\\lib\\zlib\\crc32.js","original":{"line":27,"column":0},"generated":{"line":27,"column":0}},{"source":"..\\..\\node_modules\\pako\\lib\\zlib\\crc32.js","original":{"line":28,"column":0},"generated":{"line":28,"column":0}},{"source":"..\\..\\node_modules\\pako\\lib\\zlib\\crc32.js","original":{"line":29,"column":0},"generated":{"line":29,"column":0}},{"source":"..\\..\\node_modules\\pako\\lib\\zlib\\crc32.js","original":{"line":30,"column":0},"generated":{"line":30,"column":0}},{"source":"..\\..\\node_modules\\pako\\lib\\zlib\\crc32.js","original":{"line":31,"column":0},"generated":{"line":31,"column":0}},{"source":"..\\..\\node_modules\\pako\\lib\\zlib\\crc32.js","original":{"line":32,"column":0},"generated":{"line":32,"column":0}},{"source":"..\\..\\node_modules\\pako\\lib\\zlib\\crc32.js","original":{"line":33,"column":0},"generated":{"line":33,"column":0}},{"source":"..\\..\\node_modules\\pako\\lib\\zlib\\crc32.js","original":{"line":34,"column":0},"generated":{"line":34,"column":0}},{"source":"..\\..\\node_modules\\pako\\lib\\zlib\\crc32.js","original":{"line":35,"column":0},"generated":{"line":35,"column":0}},{"source":"..\\..\\node_modules\\pako\\lib\\zlib\\crc32.js","original":{"line":36,"column":0},"generated":{"line":36,"column":0}},{"source":"..\\..\\node_modules\\pako\\lib\\zlib\\crc32.js","original":{"line":37,"column":0},"generated":{"line":37,"column":0}},{"source":"..\\..\\node_modules\\pako\\lib\\zlib\\crc32.js","original":{"line":38,"column":0},"generated":{"line":38,"column":0}},{"source":"..\\..\\node_modules\\pako\\lib\\zlib\\crc32.js","original":{"line":39,"column":0},"generated":{"line":39,"column":0}},{"source":"..\\..\\node_modules\\pako\\lib\\zlib\\crc32.js","original":{"line":40,"column":0},"generated":{"line":40,"column":0}},{"source":"..\\..\\node_modules\\pako\\lib\\zlib\\crc32.js","original":{"line":41,"column":0},"generated":{"line":41,"column":0}},{"source":"..\\..\\node_modules\\pako\\lib\\zlib\\crc32.js","original":{"line":42,"column":0},"generated":{"line":42,"column":0}},{"source":"..\\..\\node_modules\\pako\\lib\\zlib\\crc32.js","original":{"line":43,"column":0},"generated":{"line":43,"column":0}},{"source":"..\\..\\node_modules\\pako\\lib\\zlib\\crc32.js","original":{"line":44,"column":0},"generated":{"line":44,"column":0}},{"source":"..\\..\\node_modules\\pako\\lib\\zlib\\crc32.js","original":{"line":45,"column":0},"generated":{"line":45,"column":0}},{"source":"..\\..\\node_modules\\pako\\lib\\zlib\\crc32.js","original":{"line":46,"column":0},"generated":{"line":46,"column":0}},{"source":"..\\..\\node_modules\\pako\\lib\\zlib\\crc32.js","original":{"line":47,"column":0},"generated":{"line":47,"column":0}},{"source":"..\\..\\node_modules\\pako\\lib\\zlib\\crc32.js","original":{"line":48,"column":0},"generated":{"line":48,"column":0}},{"source":"..\\..\\node_modules\\pako\\lib\\zlib\\crc32.js","original":{"line":49,"column":0},"generated":{"line":49,"column":0}},{"source":"..\\..\\node_modules\\pako\\lib\\zlib\\crc32.js","original":{"line":50,"column":0},"generated":{"line":50,"column":0}},{"source":"..\\..\\node_modules\\pako\\lib\\zlib\\crc32.js","original":{"line":51,"column":0},"generated":{"line":51,"column":0}},{"source":"..\\..\\node_modules\\pako\\lib\\zlib\\crc32.js","original":{"line":52,"column":0},"generated":{"line":52,"column":0}},{"source":"..\\..\\node_modules\\pako\\lib\\zlib\\crc32.js","original":{"line":53,"column":0},"generated":{"line":53,"column":0}},{"source":"..\\..\\node_modules\\pako\\lib\\zlib\\crc32.js","original":{"line":54,"column":0},"generated":{"line":54,"column":0}},{"source":"..\\..\\node_modules\\pako\\lib\\zlib\\crc32.js","original":{"line":55,"column":0},"generated":{"line":55,"column":0}},{"source":"..\\..\\node_modules\\pako\\lib\\zlib\\crc32.js","original":{"line":56,"column":0},"generated":{"line":56,"column":0}},{"source":"..\\..\\node_modules\\pako\\lib\\zlib\\crc32.js","original":{"line":57,"column":0},"generated":{"line":57,"column":0}},{"source":"..\\..\\node_modules\\pako\\lib\\zlib\\crc32.js","original":{"line":58,"column":0},"generated":{"line":58,"column":0}},{"source":"..\\..\\node_modules\\pako\\lib\\zlib\\crc32.js","original":{"line":59,"column":0},"generated":{"line":59,"column":0}},{"source":"..\\..\\node_modules\\pako\\lib\\zlib\\crc32.js","original":{"line":60,"column":0},"generated":{"line":60,"column":0}}],"sources":{"..\\..\\node_modules\\pako\\lib\\zlib\\crc32.js":"'use strict';\r\n\r\n// Note: we can't get significant speed boost here.\r\n// So write code to minimize size - no pregenerated tables\r\n// and array tools dependencies.\r\n\r\n// (C) 1995-2013 Jean-loup Gailly and Mark Adler\r\n// (C) 2014-2017 Vitaly Puzrin and Andrey Tupitsin\r\n//\r\n// This software is provided 'as-is', without any express or implied\r\n// warranty. In no event will the authors be held liable for any damages\r\n// arising from the use of this software.\r\n//\r\n// Permission is granted to anyone to use this software for any purpose,\r\n// including commercial applications, and to alter it and redistribute it\r\n// freely, subject to the following restrictions:\r\n//\r\n// 1. The origin of this software must not be misrepresented; you must not\r\n//   claim that you wrote the original software. If you use this software\r\n//   in a product, an acknowledgment in the product documentation would be\r\n//   appreciated but is not required.\r\n// 2. Altered source versions must be plainly marked as such, and must not be\r\n//   misrepresented as being the original software.\r\n// 3. This notice may not be removed or altered from any source distribution.\r\n\r\n// Use ordinary array, since untyped makes no boost here\r\nfunction makeTable() {\r\n  var c, table = [];\r\n\r\n  for (var n = 0; n < 256; n++) {\r\n    c = n;\r\n    for (var k = 0; k < 8; k++) {\r\n      c = ((c & 1) ? (0xEDB88320 ^ (c >>> 1)) : (c >>> 1));\r\n    }\r\n    table[n] = c;\r\n  }\r\n\r\n  return table;\r\n}\r\n\r\n// Create table on load. Just 255 signed longs. Not a problem.\r\nvar crcTable = makeTable();\r\n\r\n\r\nfunction crc32(crc, buf, len, pos) {\r\n  var t = crcTable,\r\n      end = pos + len;\r\n\r\n  crc ^= -1;\r\n\r\n  for (var i = pos; i < end; i++) {\r\n    crc = (crc >>> 8) ^ t[(crc ^ buf[i]) & 0xFF];\r\n  }\r\n\r\n  return (crc ^ (-1)); // >>> 0;\r\n}\r\n\r\n\r\nmodule.exports = crc32;\r\n"},"lineCount":60}},"hash":"ad55ed7733636b42214f6ff3e307535a","cacheData":{"env":{}}}