{"dependencies":[{"name":"C:\\Users\\Ahmed\\Desktop\\Natours\\package.json","includedInParent":true,"mtime":1685934625119},{"name":"C:\\Users\\Ahmed\\Desktop\\Natours\\node_modules\\pako\\package.json","includedInParent":true,"mtime":1684371851851},{"name":"../utils/common","loc":{"line":22,"column":20}}],"generated":{"js":"'use strict';\r\n\r\n// (C) 1995-2013 Jean-loup Gailly and Mark Adler\r\n// (C) 2014-2017 Vitaly Puzrin and Andrey Tupitsin\r\n//\r\n// This software is provided 'as-is', without any express or implied\r\n// warranty. In no event will the authors be held liable for any damages\r\n// arising from the use of this software.\r\n//\r\n// Permission is granted to anyone to use this software for any purpose,\r\n// including commercial applications, and to alter it and redistribute it\r\n// freely, subject to the following restrictions:\r\n//\r\n// 1. The origin of this software must not be misrepresented; you must not\r\n//   claim that you wrote the original software. If you use this software\r\n//   in a product, an acknowledgment in the product documentation would be\r\n//   appreciated but is not required.\r\n// 2. Altered source versions must be plainly marked as such, and must not be\r\n//   misrepresented as being the original software.\r\n// 3. This notice may not be removed or altered from any source distribution.\r\n\r\nvar utils = require('../utils/common');\r\n\r\nvar MAXBITS = 15;\r\nvar ENOUGH_LENS = 852;\r\nvar ENOUGH_DISTS = 592;\r\n//var ENOUGH = (ENOUGH_LENS+ENOUGH_DISTS);\r\n\r\nvar CODES = 0;\r\nvar LENS = 1;\r\nvar DISTS = 2;\r\n\r\nvar lbase = [ /* Length codes 257..285 base */\r\n  3, 4, 5, 6, 7, 8, 9, 10, 11, 13, 15, 17, 19, 23, 27, 31,\r\n  35, 43, 51, 59, 67, 83, 99, 115, 131, 163, 195, 227, 258, 0, 0\r\n];\r\n\r\nvar lext = [ /* Length codes 257..285 extra */\r\n  16, 16, 16, 16, 16, 16, 16, 16, 17, 17, 17, 17, 18, 18, 18, 18,\r\n  19, 19, 19, 19, 20, 20, 20, 20, 21, 21, 21, 21, 16, 72, 78\r\n];\r\n\r\nvar dbase = [ /* Distance codes 0..29 base */\r\n  1, 2, 3, 4, 5, 7, 9, 13, 17, 25, 33, 49, 65, 97, 129, 193,\r\n  257, 385, 513, 769, 1025, 1537, 2049, 3073, 4097, 6145,\r\n  8193, 12289, 16385, 24577, 0, 0\r\n];\r\n\r\nvar dext = [ /* Distance codes 0..29 extra */\r\n  16, 16, 16, 16, 17, 17, 18, 18, 19, 19, 20, 20, 21, 21, 22, 22,\r\n  23, 23, 24, 24, 25, 25, 26, 26, 27, 27,\r\n  28, 28, 29, 29, 64, 64\r\n];\r\n\r\nmodule.exports = function inflate_table(type, lens, lens_index, codes, table, table_index, work, opts)\r\n{\r\n  var bits = opts.bits;\r\n      //here = opts.here; /* table entry for duplication */\r\n\r\n  var len = 0;               /* a code's length in bits */\r\n  var sym = 0;               /* index of code symbols */\r\n  var min = 0, max = 0;          /* minimum and maximum code lengths */\r\n  var root = 0;              /* number of index bits for root table */\r\n  var curr = 0;              /* number of index bits for current table */\r\n  var drop = 0;              /* code bits to drop for sub-table */\r\n  var left = 0;                   /* number of prefix codes available */\r\n  var used = 0;              /* code entries in table used */\r\n  var huff = 0;              /* Huffman code */\r\n  var incr;              /* for incrementing code, index */\r\n  var fill;              /* index for replicating entries */\r\n  var low;               /* low bits for current root entry */\r\n  var mask;              /* mask for low root bits */\r\n  var next;             /* next available space in table */\r\n  var base = null;     /* base value table to use */\r\n  var base_index = 0;\r\n//  var shoextra;    /* extra bits table to use */\r\n  var end;                    /* use base and extra for symbol > end */\r\n  var count = new utils.Buf16(MAXBITS + 1); //[MAXBITS+1];    /* number of codes of each length */\r\n  var offs = new utils.Buf16(MAXBITS + 1); //[MAXBITS+1];     /* offsets in table for each length */\r\n  var extra = null;\r\n  var extra_index = 0;\r\n\r\n  var here_bits, here_op, here_val;\r\n\r\n  /*\r\n   Process a set of code lengths to create a canonical Huffman code.  The\r\n   code lengths are lens[0..codes-1].  Each length corresponds to the\r\n   symbols 0..codes-1.  The Huffman code is generated by first sorting the\r\n   symbols by length from short to long, and retaining the symbol order\r\n   for codes with equal lengths.  Then the code starts with all zero bits\r\n   for the first code of the shortest length, and the codes are integer\r\n   increments for the same length, and zeros are appended as the length\r\n   increases.  For the deflate format, these bits are stored backwards\r\n   from their more natural integer increment ordering, and so when the\r\n   decoding tables are built in the large loop below, the integer codes\r\n   are incremented backwards.\r\n\r\n   This routine assumes, but does not check, that all of the entries in\r\n   lens[] are in the range 0..MAXBITS.  The caller must assure this.\r\n   1..MAXBITS is interpreted as that code length.  zero means that that\r\n   symbol does not occur in this code.\r\n\r\n   The codes are sorted by computing a count of codes for each length,\r\n   creating from that a table of starting indices for each length in the\r\n   sorted table, and then entering the symbols in order in the sorted\r\n   table.  The sorted table is work[], with that space being provided by\r\n   the caller.\r\n\r\n   The length counts are used for other purposes as well, i.e. finding\r\n   the minimum and maximum length codes, determining if there are any\r\n   codes at all, checking for a valid set of lengths, and looking ahead\r\n   at length counts to determine sub-table sizes when building the\r\n   decoding tables.\r\n   */\r\n\r\n  /* accumulate lengths for codes (assumes lens[] all in 0..MAXBITS) */\r\n  for (len = 0; len <= MAXBITS; len++) {\r\n    count[len] = 0;\r\n  }\r\n  for (sym = 0; sym < codes; sym++) {\r\n    count[lens[lens_index + sym]]++;\r\n  }\r\n\r\n  /* bound code lengths, force root to be within code lengths */\r\n  root = bits;\r\n  for (max = MAXBITS; max >= 1; max--) {\r\n    if (count[max] !== 0) { break; }\r\n  }\r\n  if (root > max) {\r\n    root = max;\r\n  }\r\n  if (max === 0) {                     /* no symbols to code at all */\r\n    //table.op[opts.table_index] = 64;  //here.op = (var char)64;    /* invalid code marker */\r\n    //table.bits[opts.table_index] = 1;   //here.bits = (var char)1;\r\n    //table.val[opts.table_index++] = 0;   //here.val = (var short)0;\r\n    table[table_index++] = (1 << 24) | (64 << 16) | 0;\r\n\r\n\r\n    //table.op[opts.table_index] = 64;\r\n    //table.bits[opts.table_index] = 1;\r\n    //table.val[opts.table_index++] = 0;\r\n    table[table_index++] = (1 << 24) | (64 << 16) | 0;\r\n\r\n    opts.bits = 1;\r\n    return 0;     /* no symbols, but wait for decoding to report error */\r\n  }\r\n  for (min = 1; min < max; min++) {\r\n    if (count[min] !== 0) { break; }\r\n  }\r\n  if (root < min) {\r\n    root = min;\r\n  }\r\n\r\n  /* check for an over-subscribed or incomplete set of lengths */\r\n  left = 1;\r\n  for (len = 1; len <= MAXBITS; len++) {\r\n    left <<= 1;\r\n    left -= count[len];\r\n    if (left < 0) {\r\n      return -1;\r\n    }        /* over-subscribed */\r\n  }\r\n  if (left > 0 && (type === CODES || max !== 1)) {\r\n    return -1;                      /* incomplete set */\r\n  }\r\n\r\n  /* generate offsets into symbol table for each length for sorting */\r\n  offs[1] = 0;\r\n  for (len = 1; len < MAXBITS; len++) {\r\n    offs[len + 1] = offs[len] + count[len];\r\n  }\r\n\r\n  /* sort symbols by length, by symbol order within each length */\r\n  for (sym = 0; sym < codes; sym++) {\r\n    if (lens[lens_index + sym] !== 0) {\r\n      work[offs[lens[lens_index + sym]]++] = sym;\r\n    }\r\n  }\r\n\r\n  /*\r\n   Create and fill in decoding tables.  In this loop, the table being\r\n   filled is at next and has curr index bits.  The code being used is huff\r\n   with length len.  That code is converted to an index by dropping drop\r\n   bits off of the bottom.  For codes where len is less than drop + curr,\r\n   those top drop + curr - len bits are incremented through all values to\r\n   fill the table with replicated entries.\r\n\r\n   root is the number of index bits for the root table.  When len exceeds\r\n   root, sub-tables are created pointed to by the root entry with an index\r\n   of the low root bits of huff.  This is saved in low to check for when a\r\n   new sub-table should be started.  drop is zero when the root table is\r\n   being filled, and drop is root when sub-tables are being filled.\r\n\r\n   When a new sub-table is needed, it is necessary to look ahead in the\r\n   code lengths to determine what size sub-table is needed.  The length\r\n   counts are used for this, and so count[] is decremented as codes are\r\n   entered in the tables.\r\n\r\n   used keeps track of how many table entries have been allocated from the\r\n   provided *table space.  It is checked for LENS and DIST tables against\r\n   the constants ENOUGH_LENS and ENOUGH_DISTS to guard against changes in\r\n   the initial root table size constants.  See the comments in inftrees.h\r\n   for more information.\r\n\r\n   sym increments through all symbols, and the loop terminates when\r\n   all codes of length max, i.e. all codes, have been processed.  This\r\n   routine permits incomplete codes, so another loop after this one fills\r\n   in the rest of the decoding tables with invalid code markers.\r\n   */\r\n\r\n  /* set up for code type */\r\n  // poor man optimization - use if-else instead of switch,\r\n  // to avoid deopts in old v8\r\n  if (type === CODES) {\r\n    base = extra = work;    /* dummy value--not used */\r\n    end = 19;\r\n\r\n  } else if (type === LENS) {\r\n    base = lbase;\r\n    base_index -= 257;\r\n    extra = lext;\r\n    extra_index -= 257;\r\n    end = 256;\r\n\r\n  } else {                    /* DISTS */\r\n    base = dbase;\r\n    extra = dext;\r\n    end = -1;\r\n  }\r\n\r\n  /* initialize opts for loop */\r\n  huff = 0;                   /* starting code */\r\n  sym = 0;                    /* starting code symbol */\r\n  len = min;                  /* starting code length */\r\n  next = table_index;              /* current table to fill in */\r\n  curr = root;                /* current table index bits */\r\n  drop = 0;                   /* current bits to drop from code for index */\r\n  low = -1;                   /* trigger new sub-table when len > root */\r\n  used = 1 << root;          /* use root table entries */\r\n  mask = used - 1;            /* mask for comparing low */\r\n\r\n  /* check available table space */\r\n  if ((type === LENS && used > ENOUGH_LENS) ||\r\n    (type === DISTS && used > ENOUGH_DISTS)) {\r\n    return 1;\r\n  }\r\n\r\n  /* process all codes and make table entries */\r\n  for (;;) {\r\n    /* create table entry */\r\n    here_bits = len - drop;\r\n    if (work[sym] < end) {\r\n      here_op = 0;\r\n      here_val = work[sym];\r\n    }\r\n    else if (work[sym] > end) {\r\n      here_op = extra[extra_index + work[sym]];\r\n      here_val = base[base_index + work[sym]];\r\n    }\r\n    else {\r\n      here_op = 32 + 64;         /* end of block */\r\n      here_val = 0;\r\n    }\r\n\r\n    /* replicate for those indices with low len bits equal to huff */\r\n    incr = 1 << (len - drop);\r\n    fill = 1 << curr;\r\n    min = fill;                 /* save offset to next table */\r\n    do {\r\n      fill -= incr;\r\n      table[next + (huff >> drop) + fill] = (here_bits << 24) | (here_op << 16) | here_val |0;\r\n    } while (fill !== 0);\r\n\r\n    /* backwards increment the len-bit code huff */\r\n    incr = 1 << (len - 1);\r\n    while (huff & incr) {\r\n      incr >>= 1;\r\n    }\r\n    if (incr !== 0) {\r\n      huff &= incr - 1;\r\n      huff += incr;\r\n    } else {\r\n      huff = 0;\r\n    }\r\n\r\n    /* go to next symbol, update count, len */\r\n    sym++;\r\n    if (--count[len] === 0) {\r\n      if (len === max) { break; }\r\n      len = lens[lens_index + work[sym]];\r\n    }\r\n\r\n    /* create new sub-table if needed */\r\n    if (len > root && (huff & mask) !== low) {\r\n      /* if first time, transition to sub-tables */\r\n      if (drop === 0) {\r\n        drop = root;\r\n      }\r\n\r\n      /* increment past last table */\r\n      next += min;            /* here min is 1 << curr */\r\n\r\n      /* determine length of next table */\r\n      curr = len - drop;\r\n      left = 1 << curr;\r\n      while (curr + drop < max) {\r\n        left -= count[curr + drop];\r\n        if (left <= 0) { break; }\r\n        curr++;\r\n        left <<= 1;\r\n      }\r\n\r\n      /* check for enough space */\r\n      used += 1 << curr;\r\n      if ((type === LENS && used > ENOUGH_LENS) ||\r\n        (type === DISTS && used > ENOUGH_DISTS)) {\r\n        return 1;\r\n      }\r\n\r\n      /* point entry in root table to sub-table */\r\n      low = huff & mask;\r\n      /*table.op[low] = curr;\r\n      table.bits[low] = root;\r\n      table.val[low] = next - opts.table_index;*/\r\n      table[low] = (root << 24) | (curr << 16) | (next - table_index) |0;\r\n    }\r\n  }\r\n\r\n  /* fill in remaining table entry if code is incomplete (guaranteed to have\r\n   at most one remaining entry, since if the code is incomplete, the\r\n   maximum code length that was allowed to get this far is one bit) */\r\n  if (huff !== 0) {\r\n    //table.op[next + huff] = 64;            /* invalid code marker */\r\n    //table.bits[next + huff] = len - drop;\r\n    //table.val[next + huff] = 0;\r\n    table[next + huff] = ((len - drop) << 24) | (64 << 16) |0;\r\n  }\r\n\r\n  /* set return parameters */\r\n  //opts.table_index += used;\r\n  opts.bits = root;\r\n  return 0;\r\n};\r\n","map":{"mappings":[{"source":"..\\..\\node_modules\\pako\\lib\\zlib\\inftrees.js","original":{"line":1,"column":0},"generated":{"line":1,"column":0}},{"source":"..\\..\\node_modules\\pako\\lib\\zlib\\inftrees.js","original":{"line":2,"column":0},"generated":{"line":2,"column":0}},{"source":"..\\..\\node_modules\\pako\\lib\\zlib\\inftrees.js","original":{"line":3,"column":0},"generated":{"line":3,"column":0}},{"source":"..\\..\\node_modules\\pako\\lib\\zlib\\inftrees.js","original":{"line":4,"column":0},"generated":{"line":4,"column":0}},{"source":"..\\..\\node_modules\\pako\\lib\\zlib\\inftrees.js","original":{"line":5,"column":0},"generated":{"line":5,"column":0}},{"source":"..\\..\\node_modules\\pako\\lib\\zlib\\inftrees.js","original":{"line":6,"column":0},"generated":{"line":6,"column":0}},{"source":"..\\..\\node_modules\\pako\\lib\\zlib\\inftrees.js","original":{"line":7,"column":0},"generated":{"line":7,"column":0}},{"source":"..\\..\\node_modules\\pako\\lib\\zlib\\inftrees.js","original":{"line":8,"column":0},"generated":{"line":8,"column":0}},{"source":"..\\..\\node_modules\\pako\\lib\\zlib\\inftrees.js","original":{"line":9,"column":0},"generated":{"line":9,"column":0}},{"source":"..\\..\\node_modules\\pako\\lib\\zlib\\inftrees.js","original":{"line":10,"column":0},"generated":{"line":10,"column":0}},{"source":"..\\..\\node_modules\\pako\\lib\\zlib\\inftrees.js","original":{"line":11,"column":0},"generated":{"line":11,"column":0}},{"source":"..\\..\\node_modules\\pako\\lib\\zlib\\inftrees.js","original":{"line":12,"column":0},"generated":{"line":12,"column":0}},{"source":"..\\..\\node_modules\\pako\\lib\\zlib\\inftrees.js","original":{"line":13,"column":0},"generated":{"line":13,"column":0}},{"source":"..\\..\\node_modules\\pako\\lib\\zlib\\inftrees.js","original":{"line":14,"column":0},"generated":{"line":14,"column":0}},{"source":"..\\..\\node_modules\\pako\\lib\\zlib\\inftrees.js","original":{"line":15,"column":0},"generated":{"line":15,"column":0}},{"source":"..\\..\\node_modules\\pako\\lib\\zlib\\inftrees.js","original":{"line":16,"column":0},"generated":{"line":16,"column":0}},{"source":"..\\..\\node_modules\\pako\\lib\\zlib\\inftrees.js","original":{"line":17,"column":0},"generated":{"line":17,"column":0}},{"source":"..\\..\\node_modules\\pako\\lib\\zlib\\inftrees.js","original":{"line":18,"column":0},"generated":{"line":18,"column":0}},{"source":"..\\..\\node_modules\\pako\\lib\\zlib\\inftrees.js","original":{"line":19,"column":0},"generated":{"line":19,"column":0}},{"source":"..\\..\\node_modules\\pako\\lib\\zlib\\inftrees.js","original":{"line":20,"column":0},"generated":{"line":20,"column":0}},{"source":"..\\..\\node_modules\\pako\\lib\\zlib\\inftrees.js","original":{"line":21,"column":0},"generated":{"line":21,"column":0}},{"source":"..\\..\\node_modules\\pako\\lib\\zlib\\inftrees.js","original":{"line":22,"column":0},"generated":{"line":22,"column":0}},{"source":"..\\..\\node_modules\\pako\\lib\\zlib\\inftrees.js","original":{"line":23,"column":0},"generated":{"line":23,"column":0}},{"source":"..\\..\\node_modules\\pako\\lib\\zlib\\inftrees.js","original":{"line":24,"column":0},"generated":{"line":24,"column":0}},{"source":"..\\..\\node_modules\\pako\\lib\\zlib\\inftrees.js","original":{"line":25,"column":0},"generated":{"line":25,"column":0}},{"source":"..\\..\\node_modules\\pako\\lib\\zlib\\inftrees.js","original":{"line":26,"column":0},"generated":{"line":26,"column":0}},{"source":"..\\..\\node_modules\\pako\\lib\\zlib\\inftrees.js","original":{"line":27,"column":0},"generated":{"line":27,"column":0}},{"source":"..\\..\\node_modules\\pako\\lib\\zlib\\inftrees.js","original":{"line":28,"column":0},"generated":{"line":28,"column":0}},{"source":"..\\..\\node_modules\\pako\\lib\\zlib\\inftrees.js","original":{"line":29,"column":0},"generated":{"line":29,"column":0}},{"source":"..\\..\\node_modules\\pako\\lib\\zlib\\inftrees.js","original":{"line":30,"column":0},"generated":{"line":30,"column":0}},{"source":"..\\..\\node_modules\\pako\\lib\\zlib\\inftrees.js","original":{"line":31,"column":0},"generated":{"line":31,"column":0}},{"source":"..\\..\\node_modules\\pako\\lib\\zlib\\inftrees.js","original":{"line":32,"column":0},"generated":{"line":32,"column":0}},{"source":"..\\..\\node_modules\\pako\\lib\\zlib\\inftrees.js","original":{"line":33,"column":0},"generated":{"line":33,"column":0}},{"source":"..\\..\\node_modules\\pako\\lib\\zlib\\inftrees.js","original":{"line":34,"column":0},"generated":{"line":34,"column":0}},{"source":"..\\..\\node_modules\\pako\\lib\\zlib\\inftrees.js","original":{"line":35,"column":0},"generated":{"line":35,"column":0}},{"source":"..\\..\\node_modules\\pako\\lib\\zlib\\inftrees.js","original":{"line":36,"column":0},"generated":{"line":36,"column":0}},{"source":"..\\..\\node_modules\\pako\\lib\\zlib\\inftrees.js","original":{"line":37,"column":0},"generated":{"line":37,"column":0}},{"source":"..\\..\\node_modules\\pako\\lib\\zlib\\inftrees.js","original":{"line":38,"column":0},"generated":{"line":38,"column":0}},{"source":"..\\..\\node_modules\\pako\\lib\\zlib\\inftrees.js","original":{"line":39,"column":0},"generated":{"line":39,"column":0}},{"source":"..\\..\\node_modules\\pako\\lib\\zlib\\inftrees.js","original":{"line":40,"column":0},"generated":{"line":40,"column":0}},{"source":"..\\..\\node_modules\\pako\\lib\\zlib\\inftrees.js","original":{"line":41,"column":0},"generated":{"line":41,"column":0}},{"source":"..\\..\\node_modules\\pako\\lib\\zlib\\inftrees.js","original":{"line":42,"column":0},"generated":{"line":42,"column":0}},{"source":"..\\..\\node_modules\\pako\\lib\\zlib\\inftrees.js","original":{"line":43,"column":0},"generated":{"line":43,"column":0}},{"source":"..\\..\\node_modules\\pako\\lib\\zlib\\inftrees.js","original":{"line":44,"column":0},"generated":{"line":44,"column":0}},{"source":"..\\..\\node_modules\\pako\\lib\\zlib\\inftrees.js","original":{"line":45,"column":0},"generated":{"line":45,"column":0}},{"source":"..\\..\\node_modules\\pako\\lib\\zlib\\inftrees.js","original":{"line":46,"column":0},"generated":{"line":46,"column":0}},{"source":"..\\..\\node_modules\\pako\\lib\\zlib\\inftrees.js","original":{"line":47,"column":0},"generated":{"line":47,"column":0}},{"source":"..\\..\\node_modules\\pako\\lib\\zlib\\inftrees.js","original":{"line":48,"column":0},"generated":{"line":48,"column":0}},{"source":"..\\..\\node_modules\\pako\\lib\\zlib\\inftrees.js","original":{"line":49,"column":0},"generated":{"line":49,"column":0}},{"source":"..\\..\\node_modules\\pako\\lib\\zlib\\inftrees.js","original":{"line":50,"column":0},"generated":{"line":50,"column":0}},{"source":"..\\..\\node_modules\\pako\\lib\\zlib\\inftrees.js","original":{"line":51,"column":0},"generated":{"line":51,"column":0}},{"source":"..\\..\\node_modules\\pako\\lib\\zlib\\inftrees.js","original":{"line":52,"column":0},"generated":{"line":52,"column":0}},{"source":"..\\..\\node_modules\\pako\\lib\\zlib\\inftrees.js","original":{"line":53,"column":0},"generated":{"line":53,"column":0}},{"source":"..\\..\\node_modules\\pako\\lib\\zlib\\inftrees.js","original":{"line":54,"column":0},"generated":{"line":54,"column":0}},{"source":"..\\..\\node_modules\\pako\\lib\\zlib\\inftrees.js","original":{"line":55,"column":0},"generated":{"line":55,"column":0}},{"source":"..\\..\\node_modules\\pako\\lib\\zlib\\inftrees.js","original":{"line":56,"column":0},"generated":{"line":56,"column":0}},{"source":"..\\..\\node_modules\\pako\\lib\\zlib\\inftrees.js","original":{"line":57,"column":0},"generated":{"line":57,"column":0}},{"source":"..\\..\\node_modules\\pako\\lib\\zlib\\inftrees.js","original":{"line":58,"column":0},"generated":{"line":58,"column":0}},{"source":"..\\..\\node_modules\\pako\\lib\\zlib\\inftrees.js","original":{"line":59,"column":0},"generated":{"line":59,"column":0}},{"source":"..\\..\\node_modules\\pako\\lib\\zlib\\inftrees.js","original":{"line":60,"column":0},"generated":{"line":60,"column":0}},{"source":"..\\..\\node_modules\\pako\\lib\\zlib\\inftrees.js","original":{"line":61,"column":0},"generated":{"line":61,"column":0}},{"source":"..\\..\\node_modules\\pako\\lib\\zlib\\inftrees.js","original":{"line":62,"column":0},"generated":{"line":62,"column":0}},{"source":"..\\..\\node_modules\\pako\\lib\\zlib\\inftrees.js","original":{"line":63,"column":0},"generated":{"line":63,"column":0}},{"source":"..\\..\\node_modules\\pako\\lib\\zlib\\inftrees.js","original":{"line":64,"column":0},"generated":{"line":64,"column":0}},{"source":"..\\..\\node_modules\\pako\\lib\\zlib\\inftrees.js","original":{"line":65,"column":0},"generated":{"line":65,"column":0}},{"source":"..\\..\\node_modules\\pako\\lib\\zlib\\inftrees.js","original":{"line":66,"column":0},"generated":{"line":66,"column":0}},{"source":"..\\..\\node_modules\\pako\\lib\\zlib\\inftrees.js","original":{"line":67,"column":0},"generated":{"line":67,"column":0}},{"source":"..\\..\\node_modules\\pako\\lib\\zlib\\inftrees.js","original":{"line":68,"column":0},"generated":{"line":68,"column":0}},{"source":"..\\..\\node_modules\\pako\\lib\\zlib\\inftrees.js","original":{"line":69,"column":0},"generated":{"line":69,"column":0}},{"source":"..\\..\\node_modules\\pako\\lib\\zlib\\inftrees.js","original":{"line":70,"column":0},"generated":{"line":70,"column":0}},{"source":"..\\..\\node_modules\\pako\\lib\\zlib\\inftrees.js","original":{"line":71,"column":0},"generated":{"line":71,"column":0}},{"source":"..\\..\\node_modules\\pako\\lib\\zlib\\inftrees.js","original":{"line":72,"column":0},"generated":{"line":72,"column":0}},{"source":"..\\..\\node_modules\\pako\\lib\\zlib\\inftrees.js","original":{"line":73,"column":0},"generated":{"line":73,"column":0}},{"source":"..\\..\\node_modules\\pako\\lib\\zlib\\inftrees.js","original":{"line":74,"column":0},"generated":{"line":74,"column":0}},{"source":"..\\..\\node_modules\\pako\\lib\\zlib\\inftrees.js","original":{"line":75,"column":0},"generated":{"line":75,"column":0}},{"source":"..\\..\\node_modules\\pako\\lib\\zlib\\inftrees.js","original":{"line":76,"column":0},"generated":{"line":76,"column":0}},{"source":"..\\..\\node_modules\\pako\\lib\\zlib\\inftrees.js","original":{"line":77,"column":0},"generated":{"line":77,"column":0}},{"source":"..\\..\\node_modules\\pako\\lib\\zlib\\inftrees.js","original":{"line":78,"column":0},"generated":{"line":78,"column":0}},{"source":"..\\..\\node_modules\\pako\\lib\\zlib\\inftrees.js","original":{"line":79,"column":0},"generated":{"line":79,"column":0}},{"source":"..\\..\\node_modules\\pako\\lib\\zlib\\inftrees.js","original":{"line":80,"column":0},"generated":{"line":80,"column":0}},{"source":"..\\..\\node_modules\\pako\\lib\\zlib\\inftrees.js","original":{"line":81,"column":0},"generated":{"line":81,"column":0}},{"source":"..\\..\\node_modules\\pako\\lib\\zlib\\inftrees.js","original":{"line":82,"column":0},"generated":{"line":82,"column":0}},{"source":"..\\..\\node_modules\\pako\\lib\\zlib\\inftrees.js","original":{"line":83,"column":0},"generated":{"line":83,"column":0}},{"source":"..\\..\\node_modules\\pako\\lib\\zlib\\inftrees.js","original":{"line":84,"column":0},"generated":{"line":84,"column":0}},{"source":"..\\..\\node_modules\\pako\\lib\\zlib\\inftrees.js","original":{"line":85,"column":0},"generated":{"line":85,"column":0}},{"source":"..\\..\\node_modules\\pako\\lib\\zlib\\inftrees.js","original":{"line":86,"column":0},"generated":{"line":86,"column":0}},{"source":"..\\..\\node_modules\\pako\\lib\\zlib\\inftrees.js","original":{"line":87,"column":0},"generated":{"line":87,"column":0}},{"source":"..\\..\\node_modules\\pako\\lib\\zlib\\inftrees.js","original":{"line":88,"column":0},"generated":{"line":88,"column":0}},{"source":"..\\..\\node_modules\\pako\\lib\\zlib\\inftrees.js","original":{"line":89,"column":0},"generated":{"line":89,"column":0}},{"source":"..\\..\\node_modules\\pako\\lib\\zlib\\inftrees.js","original":{"line":90,"column":0},"generated":{"line":90,"column":0}},{"source":"..\\..\\node_modules\\pako\\lib\\zlib\\inftrees.js","original":{"line":91,"column":0},"generated":{"line":91,"column":0}},{"source":"..\\..\\node_modules\\pako\\lib\\zlib\\inftrees.js","original":{"line":92,"column":0},"generated":{"line":92,"column":0}},{"source":"..\\..\\node_modules\\pako\\lib\\zlib\\inftrees.js","original":{"line":93,"column":0},"generated":{"line":93,"column":0}},{"source":"..\\..\\node_modules\\pako\\lib\\zlib\\inftrees.js","original":{"line":94,"column":0},"generated":{"line":94,"column":0}},{"source":"..\\..\\node_modules\\pako\\lib\\zlib\\inftrees.js","original":{"line":95,"column":0},"generated":{"line":95,"column":0}},{"source":"..\\..\\node_modules\\pako\\lib\\zlib\\inftrees.js","original":{"line":96,"column":0},"generated":{"line":96,"column":0}},{"source":"..\\..\\node_modules\\pako\\lib\\zlib\\inftrees.js","original":{"line":97,"column":0},"generated":{"line":97,"column":0}},{"source":"..\\..\\node_modules\\pako\\lib\\zlib\\inftrees.js","original":{"line":98,"column":0},"generated":{"line":98,"column":0}},{"source":"..\\..\\node_modules\\pako\\lib\\zlib\\inftrees.js","original":{"line":99,"column":0},"generated":{"line":99,"column":0}},{"source":"..\\..\\node_modules\\pako\\lib\\zlib\\inftrees.js","original":{"line":100,"column":0},"generated":{"line":100,"column":0}},{"source":"..\\..\\node_modules\\pako\\lib\\zlib\\inftrees.js","original":{"line":101,"column":0},"generated":{"line":101,"column":0}},{"source":"..\\..\\node_modules\\pako\\lib\\zlib\\inftrees.js","original":{"line":102,"column":0},"generated":{"line":102,"column":0}},{"source":"..\\..\\node_modules\\pako\\lib\\zlib\\inftrees.js","original":{"line":103,"column":0},"generated":{"line":103,"column":0}},{"source":"..\\..\\node_modules\\pako\\lib\\zlib\\inftrees.js","original":{"line":104,"column":0},"generated":{"line":104,"column":0}},{"source":"..\\..\\node_modules\\pako\\lib\\zlib\\inftrees.js","original":{"line":105,"column":0},"generated":{"line":105,"column":0}},{"source":"..\\..\\node_modules\\pako\\lib\\zlib\\inftrees.js","original":{"line":106,"column":0},"generated":{"line":106,"column":0}},{"source":"..\\..\\node_modules\\pako\\lib\\zlib\\inftrees.js","original":{"line":107,"column":0},"generated":{"line":107,"column":0}},{"source":"..\\..\\node_modules\\pako\\lib\\zlib\\inftrees.js","original":{"line":108,"column":0},"generated":{"line":108,"column":0}},{"source":"..\\..\\node_modules\\pako\\lib\\zlib\\inftrees.js","original":{"line":109,"column":0},"generated":{"line":109,"column":0}},{"source":"..\\..\\node_modules\\pako\\lib\\zlib\\inftrees.js","original":{"line":110,"column":0},"generated":{"line":110,"column":0}},{"source":"..\\..\\node_modules\\pako\\lib\\zlib\\inftrees.js","original":{"line":111,"column":0},"generated":{"line":111,"column":0}},{"source":"..\\..\\node_modules\\pako\\lib\\zlib\\inftrees.js","original":{"line":112,"column":0},"generated":{"line":112,"column":0}},{"source":"..\\..\\node_modules\\pako\\lib\\zlib\\inftrees.js","original":{"line":113,"column":0},"generated":{"line":113,"column":0}},{"source":"..\\..\\node_modules\\pako\\lib\\zlib\\inftrees.js","original":{"line":114,"column":0},"generated":{"line":114,"column":0}},{"source":"..\\..\\node_modules\\pako\\lib\\zlib\\inftrees.js","original":{"line":115,"column":0},"generated":{"line":115,"column":0}},{"source":"..\\..\\node_modules\\pako\\lib\\zlib\\inftrees.js","original":{"line":116,"column":0},"generated":{"line":116,"column":0}},{"source":"..\\..\\node_modules\\pako\\lib\\zlib\\inftrees.js","original":{"line":117,"column":0},"generated":{"line":117,"column":0}},{"source":"..\\..\\node_modules\\pako\\lib\\zlib\\inftrees.js","original":{"line":118,"column":0},"generated":{"line":118,"column":0}},{"source":"..\\..\\node_modules\\pako\\lib\\zlib\\inftrees.js","original":{"line":119,"column":0},"generated":{"line":119,"column":0}},{"source":"..\\..\\node_modules\\pako\\lib\\zlib\\inftrees.js","original":{"line":120,"column":0},"generated":{"line":120,"column":0}},{"source":"..\\..\\node_modules\\pako\\lib\\zlib\\inftrees.js","original":{"line":121,"column":0},"generated":{"line":121,"column":0}},{"source":"..\\..\\node_modules\\pako\\lib\\zlib\\inftrees.js","original":{"line":122,"column":0},"generated":{"line":122,"column":0}},{"source":"..\\..\\node_modules\\pako\\lib\\zlib\\inftrees.js","original":{"line":123,"column":0},"generated":{"line":123,"column":0}},{"source":"..\\..\\node_modules\\pako\\lib\\zlib\\inftrees.js","original":{"line":124,"column":0},"generated":{"line":124,"column":0}},{"source":"..\\..\\node_modules\\pako\\lib\\zlib\\inftrees.js","original":{"line":125,"column":0},"generated":{"line":125,"column":0}},{"source":"..\\..\\node_modules\\pako\\lib\\zlib\\inftrees.js","original":{"line":126,"column":0},"generated":{"line":126,"column":0}},{"source":"..\\..\\node_modules\\pako\\lib\\zlib\\inftrees.js","original":{"line":127,"column":0},"generated":{"line":127,"column":0}},{"source":"..\\..\\node_modules\\pako\\lib\\zlib\\inftrees.js","original":{"line":128,"column":0},"generated":{"line":128,"column":0}},{"source":"..\\..\\node_modules\\pako\\lib\\zlib\\inftrees.js","original":{"line":129,"column":0},"generated":{"line":129,"column":0}},{"source":"..\\..\\node_modules\\pako\\lib\\zlib\\inftrees.js","original":{"line":130,"column":0},"generated":{"line":130,"column":0}},{"source":"..\\..\\node_modules\\pako\\lib\\zlib\\inftrees.js","original":{"line":131,"column":0},"generated":{"line":131,"column":0}},{"source":"..\\..\\node_modules\\pako\\lib\\zlib\\inftrees.js","original":{"line":132,"column":0},"generated":{"line":132,"column":0}},{"source":"..\\..\\node_modules\\pako\\lib\\zlib\\inftrees.js","original":{"line":133,"column":0},"generated":{"line":133,"column":0}},{"source":"..\\..\\node_modules\\pako\\lib\\zlib\\inftrees.js","original":{"line":134,"column":0},"generated":{"line":134,"column":0}},{"source":"..\\..\\node_modules\\pako\\lib\\zlib\\inftrees.js","original":{"line":135,"column":0},"generated":{"line":135,"column":0}},{"source":"..\\..\\node_modules\\pako\\lib\\zlib\\inftrees.js","original":{"line":136,"column":0},"generated":{"line":136,"column":0}},{"source":"..\\..\\node_modules\\pako\\lib\\zlib\\inftrees.js","original":{"line":137,"column":0},"generated":{"line":137,"column":0}},{"source":"..\\..\\node_modules\\pako\\lib\\zlib\\inftrees.js","original":{"line":138,"column":0},"generated":{"line":138,"column":0}},{"source":"..\\..\\node_modules\\pako\\lib\\zlib\\inftrees.js","original":{"line":139,"column":0},"generated":{"line":139,"column":0}},{"source":"..\\..\\node_modules\\pako\\lib\\zlib\\inftrees.js","original":{"line":140,"column":0},"generated":{"line":140,"column":0}},{"source":"..\\..\\node_modules\\pako\\lib\\zlib\\inftrees.js","original":{"line":141,"column":0},"generated":{"line":141,"column":0}},{"source":"..\\..\\node_modules\\pako\\lib\\zlib\\inftrees.js","original":{"line":142,"column":0},"generated":{"line":142,"column":0}},{"source":"..\\..\\node_modules\\pako\\lib\\zlib\\inftrees.js","original":{"line":143,"column":0},"generated":{"line":143,"column":0}},{"source":"..\\..\\node_modules\\pako\\lib\\zlib\\inftrees.js","original":{"line":144,"column":0},"generated":{"line":144,"column":0}},{"source":"..\\..\\node_modules\\pako\\lib\\zlib\\inftrees.js","original":{"line":145,"column":0},"generated":{"line":145,"column":0}},{"source":"..\\..\\node_modules\\pako\\lib\\zlib\\inftrees.js","original":{"line":146,"column":0},"generated":{"line":146,"column":0}},{"source":"..\\..\\node_modules\\pako\\lib\\zlib\\inftrees.js","original":{"line":147,"column":0},"generated":{"line":147,"column":0}},{"source":"..\\..\\node_modules\\pako\\lib\\zlib\\inftrees.js","original":{"line":148,"column":0},"generated":{"line":148,"column":0}},{"source":"..\\..\\node_modules\\pako\\lib\\zlib\\inftrees.js","original":{"line":149,"column":0},"generated":{"line":149,"column":0}},{"source":"..\\..\\node_modules\\pako\\lib\\zlib\\inftrees.js","original":{"line":150,"column":0},"generated":{"line":150,"column":0}},{"source":"..\\..\\node_modules\\pako\\lib\\zlib\\inftrees.js","original":{"line":151,"column":0},"generated":{"line":151,"column":0}},{"source":"..\\..\\node_modules\\pako\\lib\\zlib\\inftrees.js","original":{"line":152,"column":0},"generated":{"line":152,"column":0}},{"source":"..\\..\\node_modules\\pako\\lib\\zlib\\inftrees.js","original":{"line":153,"column":0},"generated":{"line":153,"column":0}},{"source":"..\\..\\node_modules\\pako\\lib\\zlib\\inftrees.js","original":{"line":154,"column":0},"generated":{"line":154,"column":0}},{"source":"..\\..\\node_modules\\pako\\lib\\zlib\\inftrees.js","original":{"line":155,"column":0},"generated":{"line":155,"column":0}},{"source":"..\\..\\node_modules\\pako\\lib\\zlib\\inftrees.js","original":{"line":156,"column":0},"generated":{"line":156,"column":0}},{"source":"..\\..\\node_modules\\pako\\lib\\zlib\\inftrees.js","original":{"line":157,"column":0},"generated":{"line":157,"column":0}},{"source":"..\\..\\node_modules\\pako\\lib\\zlib\\inftrees.js","original":{"line":158,"column":0},"generated":{"line":158,"column":0}},{"source":"..\\..\\node_modules\\pako\\lib\\zlib\\inftrees.js","original":{"line":159,"column":0},"generated":{"line":159,"column":0}},{"source":"..\\..\\node_modules\\pako\\lib\\zlib\\inftrees.js","original":{"line":160,"column":0},"generated":{"line":160,"column":0}},{"source":"..\\..\\node_modules\\pako\\lib\\zlib\\inftrees.js","original":{"line":161,"column":0},"generated":{"line":161,"column":0}},{"source":"..\\..\\node_modules\\pako\\lib\\zlib\\inftrees.js","original":{"line":162,"column":0},"generated":{"line":162,"column":0}},{"source":"..\\..\\node_modules\\pako\\lib\\zlib\\inftrees.js","original":{"line":163,"column":0},"generated":{"line":163,"column":0}},{"source":"..\\..\\node_modules\\pako\\lib\\zlib\\inftrees.js","original":{"line":164,"column":0},"generated":{"line":164,"column":0}},{"source":"..\\..\\node_modules\\pako\\lib\\zlib\\inftrees.js","original":{"line":165,"column":0},"generated":{"line":165,"column":0}},{"source":"..\\..\\node_modules\\pako\\lib\\zlib\\inftrees.js","original":{"line":166,"column":0},"generated":{"line":166,"column":0}},{"source":"..\\..\\node_modules\\pako\\lib\\zlib\\inftrees.js","original":{"line":167,"column":0},"generated":{"line":167,"column":0}},{"source":"..\\..\\node_modules\\pako\\lib\\zlib\\inftrees.js","original":{"line":168,"column":0},"generated":{"line":168,"column":0}},{"source":"..\\..\\node_modules\\pako\\lib\\zlib\\inftrees.js","original":{"line":169,"column":0},"generated":{"line":169,"column":0}},{"source":"..\\..\\node_modules\\pako\\lib\\zlib\\inftrees.js","original":{"line":170,"column":0},"generated":{"line":170,"column":0}},{"source":"..\\..\\node_modules\\pako\\lib\\zlib\\inftrees.js","original":{"line":171,"column":0},"generated":{"line":171,"column":0}},{"source":"..\\..\\node_modules\\pako\\lib\\zlib\\inftrees.js","original":{"line":172,"column":0},"generated":{"line":172,"column":0}},{"source":"..\\..\\node_modules\\pako\\lib\\zlib\\inftrees.js","original":{"line":173,"column":0},"generated":{"line":173,"column":0}},{"source":"..\\..\\node_modules\\pako\\lib\\zlib\\inftrees.js","original":{"line":174,"column":0},"generated":{"line":174,"column":0}},{"source":"..\\..\\node_modules\\pako\\lib\\zlib\\inftrees.js","original":{"line":175,"column":0},"generated":{"line":175,"column":0}},{"source":"..\\..\\node_modules\\pako\\lib\\zlib\\inftrees.js","original":{"line":176,"column":0},"generated":{"line":176,"column":0}},{"source":"..\\..\\node_modules\\pako\\lib\\zlib\\inftrees.js","original":{"line":177,"column":0},"generated":{"line":177,"column":0}},{"source":"..\\..\\node_modules\\pako\\lib\\zlib\\inftrees.js","original":{"line":178,"column":0},"generated":{"line":178,"column":0}},{"source":"..\\..\\node_modules\\pako\\lib\\zlib\\inftrees.js","original":{"line":179,"column":0},"generated":{"line":179,"column":0}},{"source":"..\\..\\node_modules\\pako\\lib\\zlib\\inftrees.js","original":{"line":180,"column":0},"generated":{"line":180,"column":0}},{"source":"..\\..\\node_modules\\pako\\lib\\zlib\\inftrees.js","original":{"line":181,"column":0},"generated":{"line":181,"column":0}},{"source":"..\\..\\node_modules\\pako\\lib\\zlib\\inftrees.js","original":{"line":182,"column":0},"generated":{"line":182,"column":0}},{"source":"..\\..\\node_modules\\pako\\lib\\zlib\\inftrees.js","original":{"line":183,"column":0},"generated":{"line":183,"column":0}},{"source":"..\\..\\node_modules\\pako\\lib\\zlib\\inftrees.js","original":{"line":184,"column":0},"generated":{"line":184,"column":0}},{"source":"..\\..\\node_modules\\pako\\lib\\zlib\\inftrees.js","original":{"line":185,"column":0},"generated":{"line":185,"column":0}},{"source":"..\\..\\node_modules\\pako\\lib\\zlib\\inftrees.js","original":{"line":186,"column":0},"generated":{"line":186,"column":0}},{"source":"..\\..\\node_modules\\pako\\lib\\zlib\\inftrees.js","original":{"line":187,"column":0},"generated":{"line":187,"column":0}},{"source":"..\\..\\node_modules\\pako\\lib\\zlib\\inftrees.js","original":{"line":188,"column":0},"generated":{"line":188,"column":0}},{"source":"..\\..\\node_modules\\pako\\lib\\zlib\\inftrees.js","original":{"line":189,"column":0},"generated":{"line":189,"column":0}},{"source":"..\\..\\node_modules\\pako\\lib\\zlib\\inftrees.js","original":{"line":190,"column":0},"generated":{"line":190,"column":0}},{"source":"..\\..\\node_modules\\pako\\lib\\zlib\\inftrees.js","original":{"line":191,"column":0},"generated":{"line":191,"column":0}},{"source":"..\\..\\node_modules\\pako\\lib\\zlib\\inftrees.js","original":{"line":192,"column":0},"generated":{"line":192,"column":0}},{"source":"..\\..\\node_modules\\pako\\lib\\zlib\\inftrees.js","original":{"line":193,"column":0},"generated":{"line":193,"column":0}},{"source":"..\\..\\node_modules\\pako\\lib\\zlib\\inftrees.js","original":{"line":194,"column":0},"generated":{"line":194,"column":0}},{"source":"..\\..\\node_modules\\pako\\lib\\zlib\\inftrees.js","original":{"line":195,"column":0},"generated":{"line":195,"column":0}},{"source":"..\\..\\node_modules\\pako\\lib\\zlib\\inftrees.js","original":{"line":196,"column":0},"generated":{"line":196,"column":0}},{"source":"..\\..\\node_modules\\pako\\lib\\zlib\\inftrees.js","original":{"line":197,"column":0},"generated":{"line":197,"column":0}},{"source":"..\\..\\node_modules\\pako\\lib\\zlib\\inftrees.js","original":{"line":198,"column":0},"generated":{"line":198,"column":0}},{"source":"..\\..\\node_modules\\pako\\lib\\zlib\\inftrees.js","original":{"line":199,"column":0},"generated":{"line":199,"column":0}},{"source":"..\\..\\node_modules\\pako\\lib\\zlib\\inftrees.js","original":{"line":200,"column":0},"generated":{"line":200,"column":0}},{"source":"..\\..\\node_modules\\pako\\lib\\zlib\\inftrees.js","original":{"line":201,"column":0},"generated":{"line":201,"column":0}},{"source":"..\\..\\node_modules\\pako\\lib\\zlib\\inftrees.js","original":{"line":202,"column":0},"generated":{"line":202,"column":0}},{"source":"..\\..\\node_modules\\pako\\lib\\zlib\\inftrees.js","original":{"line":203,"column":0},"generated":{"line":203,"column":0}},{"source":"..\\..\\node_modules\\pako\\lib\\zlib\\inftrees.js","original":{"line":204,"column":0},"generated":{"line":204,"column":0}},{"source":"..\\..\\node_modules\\pako\\lib\\zlib\\inftrees.js","original":{"line":205,"column":0},"generated":{"line":205,"column":0}},{"source":"..\\..\\node_modules\\pako\\lib\\zlib\\inftrees.js","original":{"line":206,"column":0},"generated":{"line":206,"column":0}},{"source":"..\\..\\node_modules\\pako\\lib\\zlib\\inftrees.js","original":{"line":207,"column":0},"generated":{"line":207,"column":0}},{"source":"..\\..\\node_modules\\pako\\lib\\zlib\\inftrees.js","original":{"line":208,"column":0},"generated":{"line":208,"column":0}},{"source":"..\\..\\node_modules\\pako\\lib\\zlib\\inftrees.js","original":{"line":209,"column":0},"generated":{"line":209,"column":0}},{"source":"..\\..\\node_modules\\pako\\lib\\zlib\\inftrees.js","original":{"line":210,"column":0},"generated":{"line":210,"column":0}},{"source":"..\\..\\node_modules\\pako\\lib\\zlib\\inftrees.js","original":{"line":211,"column":0},"generated":{"line":211,"column":0}},{"source":"..\\..\\node_modules\\pako\\lib\\zlib\\inftrees.js","original":{"line":212,"column":0},"generated":{"line":212,"column":0}},{"source":"..\\..\\node_modules\\pako\\lib\\zlib\\inftrees.js","original":{"line":213,"column":0},"generated":{"line":213,"column":0}},{"source":"..\\..\\node_modules\\pako\\lib\\zlib\\inftrees.js","original":{"line":214,"column":0},"generated":{"line":214,"column":0}},{"source":"..\\..\\node_modules\\pako\\lib\\zlib\\inftrees.js","original":{"line":215,"column":0},"generated":{"line":215,"column":0}},{"source":"..\\..\\node_modules\\pako\\lib\\zlib\\inftrees.js","original":{"line":216,"column":0},"generated":{"line":216,"column":0}},{"source":"..\\..\\node_modules\\pako\\lib\\zlib\\inftrees.js","original":{"line":217,"column":0},"generated":{"line":217,"column":0}},{"source":"..\\..\\node_modules\\pako\\lib\\zlib\\inftrees.js","original":{"line":218,"column":0},"generated":{"line":218,"column":0}},{"source":"..\\..\\node_modules\\pako\\lib\\zlib\\inftrees.js","original":{"line":219,"column":0},"generated":{"line":219,"column":0}},{"source":"..\\..\\node_modules\\pako\\lib\\zlib\\inftrees.js","original":{"line":220,"column":0},"generated":{"line":220,"column":0}},{"source":"..\\..\\node_modules\\pako\\lib\\zlib\\inftrees.js","original":{"line":221,"column":0},"generated":{"line":221,"column":0}},{"source":"..\\..\\node_modules\\pako\\lib\\zlib\\inftrees.js","original":{"line":222,"column":0},"generated":{"line":222,"column":0}},{"source":"..\\..\\node_modules\\pako\\lib\\zlib\\inftrees.js","original":{"line":223,"column":0},"generated":{"line":223,"column":0}},{"source":"..\\..\\node_modules\\pako\\lib\\zlib\\inftrees.js","original":{"line":224,"column":0},"generated":{"line":224,"column":0}},{"source":"..\\..\\node_modules\\pako\\lib\\zlib\\inftrees.js","original":{"line":225,"column":0},"generated":{"line":225,"column":0}},{"source":"..\\..\\node_modules\\pako\\lib\\zlib\\inftrees.js","original":{"line":226,"column":0},"generated":{"line":226,"column":0}},{"source":"..\\..\\node_modules\\pako\\lib\\zlib\\inftrees.js","original":{"line":227,"column":0},"generated":{"line":227,"column":0}},{"source":"..\\..\\node_modules\\pako\\lib\\zlib\\inftrees.js","original":{"line":228,"column":0},"generated":{"line":228,"column":0}},{"source":"..\\..\\node_modules\\pako\\lib\\zlib\\inftrees.js","original":{"line":229,"column":0},"generated":{"line":229,"column":0}},{"source":"..\\..\\node_modules\\pako\\lib\\zlib\\inftrees.js","original":{"line":230,"column":0},"generated":{"line":230,"column":0}},{"source":"..\\..\\node_modules\\pako\\lib\\zlib\\inftrees.js","original":{"line":231,"column":0},"generated":{"line":231,"column":0}},{"source":"..\\..\\node_modules\\pako\\lib\\zlib\\inftrees.js","original":{"line":232,"column":0},"generated":{"line":232,"column":0}},{"source":"..\\..\\node_modules\\pako\\lib\\zlib\\inftrees.js","original":{"line":233,"column":0},"generated":{"line":233,"column":0}},{"source":"..\\..\\node_modules\\pako\\lib\\zlib\\inftrees.js","original":{"line":234,"column":0},"generated":{"line":234,"column":0}},{"source":"..\\..\\node_modules\\pako\\lib\\zlib\\inftrees.js","original":{"line":235,"column":0},"generated":{"line":235,"column":0}},{"source":"..\\..\\node_modules\\pako\\lib\\zlib\\inftrees.js","original":{"line":236,"column":0},"generated":{"line":236,"column":0}},{"source":"..\\..\\node_modules\\pako\\lib\\zlib\\inftrees.js","original":{"line":237,"column":0},"generated":{"line":237,"column":0}},{"source":"..\\..\\node_modules\\pako\\lib\\zlib\\inftrees.js","original":{"line":238,"column":0},"generated":{"line":238,"column":0}},{"source":"..\\..\\node_modules\\pako\\lib\\zlib\\inftrees.js","original":{"line":239,"column":0},"generated":{"line":239,"column":0}},{"source":"..\\..\\node_modules\\pako\\lib\\zlib\\inftrees.js","original":{"line":240,"column":0},"generated":{"line":240,"column":0}},{"source":"..\\..\\node_modules\\pako\\lib\\zlib\\inftrees.js","original":{"line":241,"column":0},"generated":{"line":241,"column":0}},{"source":"..\\..\\node_modules\\pako\\lib\\zlib\\inftrees.js","original":{"line":242,"column":0},"generated":{"line":242,"column":0}},{"source":"..\\..\\node_modules\\pako\\lib\\zlib\\inftrees.js","original":{"line":243,"column":0},"generated":{"line":243,"column":0}},{"source":"..\\..\\node_modules\\pako\\lib\\zlib\\inftrees.js","original":{"line":244,"column":0},"generated":{"line":244,"column":0}},{"source":"..\\..\\node_modules\\pako\\lib\\zlib\\inftrees.js","original":{"line":245,"column":0},"generated":{"line":245,"column":0}},{"source":"..\\..\\node_modules\\pako\\lib\\zlib\\inftrees.js","original":{"line":246,"column":0},"generated":{"line":246,"column":0}},{"source":"..\\..\\node_modules\\pako\\lib\\zlib\\inftrees.js","original":{"line":247,"column":0},"generated":{"line":247,"column":0}},{"source":"..\\..\\node_modules\\pako\\lib\\zlib\\inftrees.js","original":{"line":248,"column":0},"generated":{"line":248,"column":0}},{"source":"..\\..\\node_modules\\pako\\lib\\zlib\\inftrees.js","original":{"line":249,"column":0},"generated":{"line":249,"column":0}},{"source":"..\\..\\node_modules\\pako\\lib\\zlib\\inftrees.js","original":{"line":250,"column":0},"generated":{"line":250,"column":0}},{"source":"..\\..\\node_modules\\pako\\lib\\zlib\\inftrees.js","original":{"line":251,"column":0},"generated":{"line":251,"column":0}},{"source":"..\\..\\node_modules\\pako\\lib\\zlib\\inftrees.js","original":{"line":252,"column":0},"generated":{"line":252,"column":0}},{"source":"..\\..\\node_modules\\pako\\lib\\zlib\\inftrees.js","original":{"line":253,"column":0},"generated":{"line":253,"column":0}},{"source":"..\\..\\node_modules\\pako\\lib\\zlib\\inftrees.js","original":{"line":254,"column":0},"generated":{"line":254,"column":0}},{"source":"..\\..\\node_modules\\pako\\lib\\zlib\\inftrees.js","original":{"line":255,"column":0},"generated":{"line":255,"column":0}},{"source":"..\\..\\node_modules\\pako\\lib\\zlib\\inftrees.js","original":{"line":256,"column":0},"generated":{"line":256,"column":0}},{"source":"..\\..\\node_modules\\pako\\lib\\zlib\\inftrees.js","original":{"line":257,"column":0},"generated":{"line":257,"column":0}},{"source":"..\\..\\node_modules\\pako\\lib\\zlib\\inftrees.js","original":{"line":258,"column":0},"generated":{"line":258,"column":0}},{"source":"..\\..\\node_modules\\pako\\lib\\zlib\\inftrees.js","original":{"line":259,"column":0},"generated":{"line":259,"column":0}},{"source":"..\\..\\node_modules\\pako\\lib\\zlib\\inftrees.js","original":{"line":260,"column":0},"generated":{"line":260,"column":0}},{"source":"..\\..\\node_modules\\pako\\lib\\zlib\\inftrees.js","original":{"line":261,"column":0},"generated":{"line":261,"column":0}},{"source":"..\\..\\node_modules\\pako\\lib\\zlib\\inftrees.js","original":{"line":262,"column":0},"generated":{"line":262,"column":0}},{"source":"..\\..\\node_modules\\pako\\lib\\zlib\\inftrees.js","original":{"line":263,"column":0},"generated":{"line":263,"column":0}},{"source":"..\\..\\node_modules\\pako\\lib\\zlib\\inftrees.js","original":{"line":264,"column":0},"generated":{"line":264,"column":0}},{"source":"..\\..\\node_modules\\pako\\lib\\zlib\\inftrees.js","original":{"line":265,"column":0},"generated":{"line":265,"column":0}},{"source":"..\\..\\node_modules\\pako\\lib\\zlib\\inftrees.js","original":{"line":266,"column":0},"generated":{"line":266,"column":0}},{"source":"..\\..\\node_modules\\pako\\lib\\zlib\\inftrees.js","original":{"line":267,"column":0},"generated":{"line":267,"column":0}},{"source":"..\\..\\node_modules\\pako\\lib\\zlib\\inftrees.js","original":{"line":268,"column":0},"generated":{"line":268,"column":0}},{"source":"..\\..\\node_modules\\pako\\lib\\zlib\\inftrees.js","original":{"line":269,"column":0},"generated":{"line":269,"column":0}},{"source":"..\\..\\node_modules\\pako\\lib\\zlib\\inftrees.js","original":{"line":270,"column":0},"generated":{"line":270,"column":0}},{"source":"..\\..\\node_modules\\pako\\lib\\zlib\\inftrees.js","original":{"line":271,"column":0},"generated":{"line":271,"column":0}},{"source":"..\\..\\node_modules\\pako\\lib\\zlib\\inftrees.js","original":{"line":272,"column":0},"generated":{"line":272,"column":0}},{"source":"..\\..\\node_modules\\pako\\lib\\zlib\\inftrees.js","original":{"line":273,"column":0},"generated":{"line":273,"column":0}},{"source":"..\\..\\node_modules\\pako\\lib\\zlib\\inftrees.js","original":{"line":274,"column":0},"generated":{"line":274,"column":0}},{"source":"..\\..\\node_modules\\pako\\lib\\zlib\\inftrees.js","original":{"line":275,"column":0},"generated":{"line":275,"column":0}},{"source":"..\\..\\node_modules\\pako\\lib\\zlib\\inftrees.js","original":{"line":276,"column":0},"generated":{"line":276,"column":0}},{"source":"..\\..\\node_modules\\pako\\lib\\zlib\\inftrees.js","original":{"line":277,"column":0},"generated":{"line":277,"column":0}},{"source":"..\\..\\node_modules\\pako\\lib\\zlib\\inftrees.js","original":{"line":278,"column":0},"generated":{"line":278,"column":0}},{"source":"..\\..\\node_modules\\pako\\lib\\zlib\\inftrees.js","original":{"line":279,"column":0},"generated":{"line":279,"column":0}},{"source":"..\\..\\node_modules\\pako\\lib\\zlib\\inftrees.js","original":{"line":280,"column":0},"generated":{"line":280,"column":0}},{"source":"..\\..\\node_modules\\pako\\lib\\zlib\\inftrees.js","original":{"line":281,"column":0},"generated":{"line":281,"column":0}},{"source":"..\\..\\node_modules\\pako\\lib\\zlib\\inftrees.js","original":{"line":282,"column":0},"generated":{"line":282,"column":0}},{"source":"..\\..\\node_modules\\pako\\lib\\zlib\\inftrees.js","original":{"line":283,"column":0},"generated":{"line":283,"column":0}},{"source":"..\\..\\node_modules\\pako\\lib\\zlib\\inftrees.js","original":{"line":284,"column":0},"generated":{"line":284,"column":0}},{"source":"..\\..\\node_modules\\pako\\lib\\zlib\\inftrees.js","original":{"line":285,"column":0},"generated":{"line":285,"column":0}},{"source":"..\\..\\node_modules\\pako\\lib\\zlib\\inftrees.js","original":{"line":286,"column":0},"generated":{"line":286,"column":0}},{"source":"..\\..\\node_modules\\pako\\lib\\zlib\\inftrees.js","original":{"line":287,"column":0},"generated":{"line":287,"column":0}},{"source":"..\\..\\node_modules\\pako\\lib\\zlib\\inftrees.js","original":{"line":288,"column":0},"generated":{"line":288,"column":0}},{"source":"..\\..\\node_modules\\pako\\lib\\zlib\\inftrees.js","original":{"line":289,"column":0},"generated":{"line":289,"column":0}},{"source":"..\\..\\node_modules\\pako\\lib\\zlib\\inftrees.js","original":{"line":290,"column":0},"generated":{"line":290,"column":0}},{"source":"..\\..\\node_modules\\pako\\lib\\zlib\\inftrees.js","original":{"line":291,"column":0},"generated":{"line":291,"column":0}},{"source":"..\\..\\node_modules\\pako\\lib\\zlib\\inftrees.js","original":{"line":292,"column":0},"generated":{"line":292,"column":0}},{"source":"..\\..\\node_modules\\pako\\lib\\zlib\\inftrees.js","original":{"line":293,"column":0},"generated":{"line":293,"column":0}},{"source":"..\\..\\node_modules\\pako\\lib\\zlib\\inftrees.js","original":{"line":294,"column":0},"generated":{"line":294,"column":0}},{"source":"..\\..\\node_modules\\pako\\lib\\zlib\\inftrees.js","original":{"line":295,"column":0},"generated":{"line":295,"column":0}},{"source":"..\\..\\node_modules\\pako\\lib\\zlib\\inftrees.js","original":{"line":296,"column":0},"generated":{"line":296,"column":0}},{"source":"..\\..\\node_modules\\pako\\lib\\zlib\\inftrees.js","original":{"line":297,"column":0},"generated":{"line":297,"column":0}},{"source":"..\\..\\node_modules\\pako\\lib\\zlib\\inftrees.js","original":{"line":298,"column":0},"generated":{"line":298,"column":0}},{"source":"..\\..\\node_modules\\pako\\lib\\zlib\\inftrees.js","original":{"line":299,"column":0},"generated":{"line":299,"column":0}},{"source":"..\\..\\node_modules\\pako\\lib\\zlib\\inftrees.js","original":{"line":300,"column":0},"generated":{"line":300,"column":0}},{"source":"..\\..\\node_modules\\pako\\lib\\zlib\\inftrees.js","original":{"line":301,"column":0},"generated":{"line":301,"column":0}},{"source":"..\\..\\node_modules\\pako\\lib\\zlib\\inftrees.js","original":{"line":302,"column":0},"generated":{"line":302,"column":0}},{"source":"..\\..\\node_modules\\pako\\lib\\zlib\\inftrees.js","original":{"line":303,"column":0},"generated":{"line":303,"column":0}},{"source":"..\\..\\node_modules\\pako\\lib\\zlib\\inftrees.js","original":{"line":304,"column":0},"generated":{"line":304,"column":0}},{"source":"..\\..\\node_modules\\pako\\lib\\zlib\\inftrees.js","original":{"line":305,"column":0},"generated":{"line":305,"column":0}},{"source":"..\\..\\node_modules\\pako\\lib\\zlib\\inftrees.js","original":{"line":306,"column":0},"generated":{"line":306,"column":0}},{"source":"..\\..\\node_modules\\pako\\lib\\zlib\\inftrees.js","original":{"line":307,"column":0},"generated":{"line":307,"column":0}},{"source":"..\\..\\node_modules\\pako\\lib\\zlib\\inftrees.js","original":{"line":308,"column":0},"generated":{"line":308,"column":0}},{"source":"..\\..\\node_modules\\pako\\lib\\zlib\\inftrees.js","original":{"line":309,"column":0},"generated":{"line":309,"column":0}},{"source":"..\\..\\node_modules\\pako\\lib\\zlib\\inftrees.js","original":{"line":310,"column":0},"generated":{"line":310,"column":0}},{"source":"..\\..\\node_modules\\pako\\lib\\zlib\\inftrees.js","original":{"line":311,"column":0},"generated":{"line":311,"column":0}},{"source":"..\\..\\node_modules\\pako\\lib\\zlib\\inftrees.js","original":{"line":312,"column":0},"generated":{"line":312,"column":0}},{"source":"..\\..\\node_modules\\pako\\lib\\zlib\\inftrees.js","original":{"line":313,"column":0},"generated":{"line":313,"column":0}},{"source":"..\\..\\node_modules\\pako\\lib\\zlib\\inftrees.js","original":{"line":314,"column":0},"generated":{"line":314,"column":0}},{"source":"..\\..\\node_modules\\pako\\lib\\zlib\\inftrees.js","original":{"line":315,"column":0},"generated":{"line":315,"column":0}},{"source":"..\\..\\node_modules\\pako\\lib\\zlib\\inftrees.js","original":{"line":316,"column":0},"generated":{"line":316,"column":0}},{"source":"..\\..\\node_modules\\pako\\lib\\zlib\\inftrees.js","original":{"line":317,"column":0},"generated":{"line":317,"column":0}},{"source":"..\\..\\node_modules\\pako\\lib\\zlib\\inftrees.js","original":{"line":318,"column":0},"generated":{"line":318,"column":0}},{"source":"..\\..\\node_modules\\pako\\lib\\zlib\\inftrees.js","original":{"line":319,"column":0},"generated":{"line":319,"column":0}},{"source":"..\\..\\node_modules\\pako\\lib\\zlib\\inftrees.js","original":{"line":320,"column":0},"generated":{"line":320,"column":0}},{"source":"..\\..\\node_modules\\pako\\lib\\zlib\\inftrees.js","original":{"line":321,"column":0},"generated":{"line":321,"column":0}},{"source":"..\\..\\node_modules\\pako\\lib\\zlib\\inftrees.js","original":{"line":322,"column":0},"generated":{"line":322,"column":0}},{"source":"..\\..\\node_modules\\pako\\lib\\zlib\\inftrees.js","original":{"line":323,"column":0},"generated":{"line":323,"column":0}},{"source":"..\\..\\node_modules\\pako\\lib\\zlib\\inftrees.js","original":{"line":324,"column":0},"generated":{"line":324,"column":0}},{"source":"..\\..\\node_modules\\pako\\lib\\zlib\\inftrees.js","original":{"line":325,"column":0},"generated":{"line":325,"column":0}},{"source":"..\\..\\node_modules\\pako\\lib\\zlib\\inftrees.js","original":{"line":326,"column":0},"generated":{"line":326,"column":0}},{"source":"..\\..\\node_modules\\pako\\lib\\zlib\\inftrees.js","original":{"line":327,"column":0},"generated":{"line":327,"column":0}},{"source":"..\\..\\node_modules\\pako\\lib\\zlib\\inftrees.js","original":{"line":328,"column":0},"generated":{"line":328,"column":0}},{"source":"..\\..\\node_modules\\pako\\lib\\zlib\\inftrees.js","original":{"line":329,"column":0},"generated":{"line":329,"column":0}},{"source":"..\\..\\node_modules\\pako\\lib\\zlib\\inftrees.js","original":{"line":330,"column":0},"generated":{"line":330,"column":0}},{"source":"..\\..\\node_modules\\pako\\lib\\zlib\\inftrees.js","original":{"line":331,"column":0},"generated":{"line":331,"column":0}},{"source":"..\\..\\node_modules\\pako\\lib\\zlib\\inftrees.js","original":{"line":332,"column":0},"generated":{"line":332,"column":0}},{"source":"..\\..\\node_modules\\pako\\lib\\zlib\\inftrees.js","original":{"line":333,"column":0},"generated":{"line":333,"column":0}},{"source":"..\\..\\node_modules\\pako\\lib\\zlib\\inftrees.js","original":{"line":334,"column":0},"generated":{"line":334,"column":0}},{"source":"..\\..\\node_modules\\pako\\lib\\zlib\\inftrees.js","original":{"line":335,"column":0},"generated":{"line":335,"column":0}},{"source":"..\\..\\node_modules\\pako\\lib\\zlib\\inftrees.js","original":{"line":336,"column":0},"generated":{"line":336,"column":0}},{"source":"..\\..\\node_modules\\pako\\lib\\zlib\\inftrees.js","original":{"line":337,"column":0},"generated":{"line":337,"column":0}},{"source":"..\\..\\node_modules\\pako\\lib\\zlib\\inftrees.js","original":{"line":338,"column":0},"generated":{"line":338,"column":0}},{"source":"..\\..\\node_modules\\pako\\lib\\zlib\\inftrees.js","original":{"line":339,"column":0},"generated":{"line":339,"column":0}},{"source":"..\\..\\node_modules\\pako\\lib\\zlib\\inftrees.js","original":{"line":340,"column":0},"generated":{"line":340,"column":0}},{"source":"..\\..\\node_modules\\pako\\lib\\zlib\\inftrees.js","original":{"line":341,"column":0},"generated":{"line":341,"column":0}},{"source":"..\\..\\node_modules\\pako\\lib\\zlib\\inftrees.js","original":{"line":342,"column":0},"generated":{"line":342,"column":0}},{"source":"..\\..\\node_modules\\pako\\lib\\zlib\\inftrees.js","original":{"line":343,"column":0},"generated":{"line":343,"column":0}},{"source":"..\\..\\node_modules\\pako\\lib\\zlib\\inftrees.js","original":{"line":344,"column":0},"generated":{"line":344,"column":0}}],"sources":{"..\\..\\node_modules\\pako\\lib\\zlib\\inftrees.js":"'use strict';\r\n\r\n// (C) 1995-2013 Jean-loup Gailly and Mark Adler\r\n// (C) 2014-2017 Vitaly Puzrin and Andrey Tupitsin\r\n//\r\n// This software is provided 'as-is', without any express or implied\r\n// warranty. In no event will the authors be held liable for any damages\r\n// arising from the use of this software.\r\n//\r\n// Permission is granted to anyone to use this software for any purpose,\r\n// including commercial applications, and to alter it and redistribute it\r\n// freely, subject to the following restrictions:\r\n//\r\n// 1. The origin of this software must not be misrepresented; you must not\r\n//   claim that you wrote the original software. If you use this software\r\n//   in a product, an acknowledgment in the product documentation would be\r\n//   appreciated but is not required.\r\n// 2. Altered source versions must be plainly marked as such, and must not be\r\n//   misrepresented as being the original software.\r\n// 3. This notice may not be removed or altered from any source distribution.\r\n\r\nvar utils = require('../utils/common');\r\n\r\nvar MAXBITS = 15;\r\nvar ENOUGH_LENS = 852;\r\nvar ENOUGH_DISTS = 592;\r\n//var ENOUGH = (ENOUGH_LENS+ENOUGH_DISTS);\r\n\r\nvar CODES = 0;\r\nvar LENS = 1;\r\nvar DISTS = 2;\r\n\r\nvar lbase = [ /* Length codes 257..285 base */\r\n  3, 4, 5, 6, 7, 8, 9, 10, 11, 13, 15, 17, 19, 23, 27, 31,\r\n  35, 43, 51, 59, 67, 83, 99, 115, 131, 163, 195, 227, 258, 0, 0\r\n];\r\n\r\nvar lext = [ /* Length codes 257..285 extra */\r\n  16, 16, 16, 16, 16, 16, 16, 16, 17, 17, 17, 17, 18, 18, 18, 18,\r\n  19, 19, 19, 19, 20, 20, 20, 20, 21, 21, 21, 21, 16, 72, 78\r\n];\r\n\r\nvar dbase = [ /* Distance codes 0..29 base */\r\n  1, 2, 3, 4, 5, 7, 9, 13, 17, 25, 33, 49, 65, 97, 129, 193,\r\n  257, 385, 513, 769, 1025, 1537, 2049, 3073, 4097, 6145,\r\n  8193, 12289, 16385, 24577, 0, 0\r\n];\r\n\r\nvar dext = [ /* Distance codes 0..29 extra */\r\n  16, 16, 16, 16, 17, 17, 18, 18, 19, 19, 20, 20, 21, 21, 22, 22,\r\n  23, 23, 24, 24, 25, 25, 26, 26, 27, 27,\r\n  28, 28, 29, 29, 64, 64\r\n];\r\n\r\nmodule.exports = function inflate_table(type, lens, lens_index, codes, table, table_index, work, opts)\r\n{\r\n  var bits = opts.bits;\r\n      //here = opts.here; /* table entry for duplication */\r\n\r\n  var len = 0;               /* a code's length in bits */\r\n  var sym = 0;               /* index of code symbols */\r\n  var min = 0, max = 0;          /* minimum and maximum code lengths */\r\n  var root = 0;              /* number of index bits for root table */\r\n  var curr = 0;              /* number of index bits for current table */\r\n  var drop = 0;              /* code bits to drop for sub-table */\r\n  var left = 0;                   /* number of prefix codes available */\r\n  var used = 0;              /* code entries in table used */\r\n  var huff = 0;              /* Huffman code */\r\n  var incr;              /* for incrementing code, index */\r\n  var fill;              /* index for replicating entries */\r\n  var low;               /* low bits for current root entry */\r\n  var mask;              /* mask for low root bits */\r\n  var next;             /* next available space in table */\r\n  var base = null;     /* base value table to use */\r\n  var base_index = 0;\r\n//  var shoextra;    /* extra bits table to use */\r\n  var end;                    /* use base and extra for symbol > end */\r\n  var count = new utils.Buf16(MAXBITS + 1); //[MAXBITS+1];    /* number of codes of each length */\r\n  var offs = new utils.Buf16(MAXBITS + 1); //[MAXBITS+1];     /* offsets in table for each length */\r\n  var extra = null;\r\n  var extra_index = 0;\r\n\r\n  var here_bits, here_op, here_val;\r\n\r\n  /*\r\n   Process a set of code lengths to create a canonical Huffman code.  The\r\n   code lengths are lens[0..codes-1].  Each length corresponds to the\r\n   symbols 0..codes-1.  The Huffman code is generated by first sorting the\r\n   symbols by length from short to long, and retaining the symbol order\r\n   for codes with equal lengths.  Then the code starts with all zero bits\r\n   for the first code of the shortest length, and the codes are integer\r\n   increments for the same length, and zeros are appended as the length\r\n   increases.  For the deflate format, these bits are stored backwards\r\n   from their more natural integer increment ordering, and so when the\r\n   decoding tables are built in the large loop below, the integer codes\r\n   are incremented backwards.\r\n\r\n   This routine assumes, but does not check, that all of the entries in\r\n   lens[] are in the range 0..MAXBITS.  The caller must assure this.\r\n   1..MAXBITS is interpreted as that code length.  zero means that that\r\n   symbol does not occur in this code.\r\n\r\n   The codes are sorted by computing a count of codes for each length,\r\n   creating from that a table of starting indices for each length in the\r\n   sorted table, and then entering the symbols in order in the sorted\r\n   table.  The sorted table is work[], with that space being provided by\r\n   the caller.\r\n\r\n   The length counts are used for other purposes as well, i.e. finding\r\n   the minimum and maximum length codes, determining if there are any\r\n   codes at all, checking for a valid set of lengths, and looking ahead\r\n   at length counts to determine sub-table sizes when building the\r\n   decoding tables.\r\n   */\r\n\r\n  /* accumulate lengths for codes (assumes lens[] all in 0..MAXBITS) */\r\n  for (len = 0; len <= MAXBITS; len++) {\r\n    count[len] = 0;\r\n  }\r\n  for (sym = 0; sym < codes; sym++) {\r\n    count[lens[lens_index + sym]]++;\r\n  }\r\n\r\n  /* bound code lengths, force root to be within code lengths */\r\n  root = bits;\r\n  for (max = MAXBITS; max >= 1; max--) {\r\n    if (count[max] !== 0) { break; }\r\n  }\r\n  if (root > max) {\r\n    root = max;\r\n  }\r\n  if (max === 0) {                     /* no symbols to code at all */\r\n    //table.op[opts.table_index] = 64;  //here.op = (var char)64;    /* invalid code marker */\r\n    //table.bits[opts.table_index] = 1;   //here.bits = (var char)1;\r\n    //table.val[opts.table_index++] = 0;   //here.val = (var short)0;\r\n    table[table_index++] = (1 << 24) | (64 << 16) | 0;\r\n\r\n\r\n    //table.op[opts.table_index] = 64;\r\n    //table.bits[opts.table_index] = 1;\r\n    //table.val[opts.table_index++] = 0;\r\n    table[table_index++] = (1 << 24) | (64 << 16) | 0;\r\n\r\n    opts.bits = 1;\r\n    return 0;     /* no symbols, but wait for decoding to report error */\r\n  }\r\n  for (min = 1; min < max; min++) {\r\n    if (count[min] !== 0) { break; }\r\n  }\r\n  if (root < min) {\r\n    root = min;\r\n  }\r\n\r\n  /* check for an over-subscribed or incomplete set of lengths */\r\n  left = 1;\r\n  for (len = 1; len <= MAXBITS; len++) {\r\n    left <<= 1;\r\n    left -= count[len];\r\n    if (left < 0) {\r\n      return -1;\r\n    }        /* over-subscribed */\r\n  }\r\n  if (left > 0 && (type === CODES || max !== 1)) {\r\n    return -1;                      /* incomplete set */\r\n  }\r\n\r\n  /* generate offsets into symbol table for each length for sorting */\r\n  offs[1] = 0;\r\n  for (len = 1; len < MAXBITS; len++) {\r\n    offs[len + 1] = offs[len] + count[len];\r\n  }\r\n\r\n  /* sort symbols by length, by symbol order within each length */\r\n  for (sym = 0; sym < codes; sym++) {\r\n    if (lens[lens_index + sym] !== 0) {\r\n      work[offs[lens[lens_index + sym]]++] = sym;\r\n    }\r\n  }\r\n\r\n  /*\r\n   Create and fill in decoding tables.  In this loop, the table being\r\n   filled is at next and has curr index bits.  The code being used is huff\r\n   with length len.  That code is converted to an index by dropping drop\r\n   bits off of the bottom.  For codes where len is less than drop + curr,\r\n   those top drop + curr - len bits are incremented through all values to\r\n   fill the table with replicated entries.\r\n\r\n   root is the number of index bits for the root table.  When len exceeds\r\n   root, sub-tables are created pointed to by the root entry with an index\r\n   of the low root bits of huff.  This is saved in low to check for when a\r\n   new sub-table should be started.  drop is zero when the root table is\r\n   being filled, and drop is root when sub-tables are being filled.\r\n\r\n   When a new sub-table is needed, it is necessary to look ahead in the\r\n   code lengths to determine what size sub-table is needed.  The length\r\n   counts are used for this, and so count[] is decremented as codes are\r\n   entered in the tables.\r\n\r\n   used keeps track of how many table entries have been allocated from the\r\n   provided *table space.  It is checked for LENS and DIST tables against\r\n   the constants ENOUGH_LENS and ENOUGH_DISTS to guard against changes in\r\n   the initial root table size constants.  See the comments in inftrees.h\r\n   for more information.\r\n\r\n   sym increments through all symbols, and the loop terminates when\r\n   all codes of length max, i.e. all codes, have been processed.  This\r\n   routine permits incomplete codes, so another loop after this one fills\r\n   in the rest of the decoding tables with invalid code markers.\r\n   */\r\n\r\n  /* set up for code type */\r\n  // poor man optimization - use if-else instead of switch,\r\n  // to avoid deopts in old v8\r\n  if (type === CODES) {\r\n    base = extra = work;    /* dummy value--not used */\r\n    end = 19;\r\n\r\n  } else if (type === LENS) {\r\n    base = lbase;\r\n    base_index -= 257;\r\n    extra = lext;\r\n    extra_index -= 257;\r\n    end = 256;\r\n\r\n  } else {                    /* DISTS */\r\n    base = dbase;\r\n    extra = dext;\r\n    end = -1;\r\n  }\r\n\r\n  /* initialize opts for loop */\r\n  huff = 0;                   /* starting code */\r\n  sym = 0;                    /* starting code symbol */\r\n  len = min;                  /* starting code length */\r\n  next = table_index;              /* current table to fill in */\r\n  curr = root;                /* current table index bits */\r\n  drop = 0;                   /* current bits to drop from code for index */\r\n  low = -1;                   /* trigger new sub-table when len > root */\r\n  used = 1 << root;          /* use root table entries */\r\n  mask = used - 1;            /* mask for comparing low */\r\n\r\n  /* check available table space */\r\n  if ((type === LENS && used > ENOUGH_LENS) ||\r\n    (type === DISTS && used > ENOUGH_DISTS)) {\r\n    return 1;\r\n  }\r\n\r\n  /* process all codes and make table entries */\r\n  for (;;) {\r\n    /* create table entry */\r\n    here_bits = len - drop;\r\n    if (work[sym] < end) {\r\n      here_op = 0;\r\n      here_val = work[sym];\r\n    }\r\n    else if (work[sym] > end) {\r\n      here_op = extra[extra_index + work[sym]];\r\n      here_val = base[base_index + work[sym]];\r\n    }\r\n    else {\r\n      here_op = 32 + 64;         /* end of block */\r\n      here_val = 0;\r\n    }\r\n\r\n    /* replicate for those indices with low len bits equal to huff */\r\n    incr = 1 << (len - drop);\r\n    fill = 1 << curr;\r\n    min = fill;                 /* save offset to next table */\r\n    do {\r\n      fill -= incr;\r\n      table[next + (huff >> drop) + fill] = (here_bits << 24) | (here_op << 16) | here_val |0;\r\n    } while (fill !== 0);\r\n\r\n    /* backwards increment the len-bit code huff */\r\n    incr = 1 << (len - 1);\r\n    while (huff & incr) {\r\n      incr >>= 1;\r\n    }\r\n    if (incr !== 0) {\r\n      huff &= incr - 1;\r\n      huff += incr;\r\n    } else {\r\n      huff = 0;\r\n    }\r\n\r\n    /* go to next symbol, update count, len */\r\n    sym++;\r\n    if (--count[len] === 0) {\r\n      if (len === max) { break; }\r\n      len = lens[lens_index + work[sym]];\r\n    }\r\n\r\n    /* create new sub-table if needed */\r\n    if (len > root && (huff & mask) !== low) {\r\n      /* if first time, transition to sub-tables */\r\n      if (drop === 0) {\r\n        drop = root;\r\n      }\r\n\r\n      /* increment past last table */\r\n      next += min;            /* here min is 1 << curr */\r\n\r\n      /* determine length of next table */\r\n      curr = len - drop;\r\n      left = 1 << curr;\r\n      while (curr + drop < max) {\r\n        left -= count[curr + drop];\r\n        if (left <= 0) { break; }\r\n        curr++;\r\n        left <<= 1;\r\n      }\r\n\r\n      /* check for enough space */\r\n      used += 1 << curr;\r\n      if ((type === LENS && used > ENOUGH_LENS) ||\r\n        (type === DISTS && used > ENOUGH_DISTS)) {\r\n        return 1;\r\n      }\r\n\r\n      /* point entry in root table to sub-table */\r\n      low = huff & mask;\r\n      /*table.op[low] = curr;\r\n      table.bits[low] = root;\r\n      table.val[low] = next - opts.table_index;*/\r\n      table[low] = (root << 24) | (curr << 16) | (next - table_index) |0;\r\n    }\r\n  }\r\n\r\n  /* fill in remaining table entry if code is incomplete (guaranteed to have\r\n   at most one remaining entry, since if the code is incomplete, the\r\n   maximum code length that was allowed to get this far is one bit) */\r\n  if (huff !== 0) {\r\n    //table.op[next + huff] = 64;            /* invalid code marker */\r\n    //table.bits[next + huff] = len - drop;\r\n    //table.val[next + huff] = 0;\r\n    table[next + huff] = ((len - drop) << 24) | (64 << 16) |0;\r\n  }\r\n\r\n  /* set return parameters */\r\n  //opts.table_index += used;\r\n  opts.bits = root;\r\n  return 0;\r\n};\r\n"},"lineCount":344}},"hash":"f47cdea5c10f1e297cd6186356c0637e","cacheData":{"env":{}}}